{"cameraMode":{"drawMode":0,"name":"Shaded","section":"Shading Mode"},"sceneLighting":true,"audioPlay":false,"sceneViewState":{"m_AlwaysRefresh":false,"showFog":true,"showSkybox":true,"showFlares":true,"showImageEffects":true,"showParticleSystems":true,"showVisualEffectGraphs":true,"m_FxEnabled":true},"in2DMode":false,"pivot":{"x":338.5401306152344,"y":197.9847869873047,"z":775.5180053710938},"rotation":{"x":-0.15157391130924226,"y":0.22529584169387818,"z":-0.035520877689123157,"w":-0.9618273973464966},"size":12.12435531616211,"orthographic":false}